MANIFEST.in
setup.py
src/super_calculator_berkay/__init__.py
src/super_calculator_berkay/add_subtract.py
src/super_calculator_berkay/multiply_divide.py
src/super_calculator_berkay.egg-info/PKG-INFO
src/super_calculator_berkay.egg-info/SOURCES.txt
src/super_calculator_berkay.egg-info/dependency_links.txt
src/super_calculator_berkay.egg-info/top_level.txt
tests/__init__.py
tests/test_modules.py